odoo/addons/l10n_br_purchase/README.rst
odoo/addons/l10n_br_purchase/__init__.py
odoo/addons/l10n_br_purchase/__manifest__.py
odoo/addons/l10n_br_purchase/hooks.py
odoo/addons/l10n_br_purchase/data/company.xml
odoo/addons/l10n_br_purchase/demo/company.xml
odoo/addons/l10n_br_purchase/demo/fiscal_operation_generic.xml
odoo/addons/l10n_br_purchase/demo/fiscal_operation_simple.xml
odoo/addons/l10n_br_purchase/demo/l10n_br_purchase.xml
odoo/addons/l10n_br_purchase/demo/product.xml
odoo/addons/l10n_br_purchase/i18n/l10n_br_purchase.pot
odoo/addons/l10n_br_purchase/i18n/pt_BR.po
odoo/addons/l10n_br_purchase/models/__init__.py
odoo/addons/l10n_br_purchase/models/account_move.py
odoo/addons/l10n_br_purchase/models/purchase_order.py
odoo/addons/l10n_br_purchase/models/purchase_order_line.py
odoo/addons/l10n_br_purchase/models/res_company.py
odoo/addons/l10n_br_purchase/readme/CONFIGURE.rst
odoo/addons/l10n_br_purchase/readme/CONTRIBUTORS.rst
odoo/addons/l10n_br_purchase/readme/CREDITS.rst
odoo/addons/l10n_br_purchase/readme/DESCRIPTION.rst
odoo/addons/l10n_br_purchase/readme/HISTORY.rst
odoo/addons/l10n_br_purchase/readme/INSTALL.rst
odoo/addons/l10n_br_purchase/readme/ROADMAP.rst
odoo/addons/l10n_br_purchase/readme/USAGE.rst
odoo/addons/l10n_br_purchase/reports/__init__.py
odoo/addons/l10n_br_purchase/reports/purchase_order_templates.xml
odoo/addons/l10n_br_purchase/reports/purchase_report.py
odoo/addons/l10n_br_purchase/reports/purchase_report_views.xml
odoo/addons/l10n_br_purchase/security/ir.model.access.csv
odoo/addons/l10n_br_purchase/static/description/icon.png
odoo/addons/l10n_br_purchase/static/description/index.html
odoo/addons/l10n_br_purchase/tests/__init__.py
odoo/addons/l10n_br_purchase/tests/test_l10n_br_purchase.py
odoo/addons/l10n_br_purchase/tests/test_l10n_br_purchase_sn.py
odoo/addons/l10n_br_purchase/views/purchase_view.xml
odoo/addons/l10n_br_purchase/views/res_company_view.xml
odoo14_addon_l10n_br_purchase-14.0.3.11.1.dist-info/METADATA
odoo14_addon_l10n_br_purchase-14.0.3.11.1.dist-info/WHEEL
odoo14_addon_l10n_br_purchase-14.0.3.11.1.dist-info/top_level.txt
odoo14_addon_l10n_br_purchase-14.0.3.11.1.dist-info/RECORD
